{
  "data": {
    "id": 1,
    "email": "jofix21@gmail.com",
    "name": "ABCDEF",
    "business_type": 7,
    "contact_number": "09324325006",
    "contact_person": "Mark Aboganda",
    "image": "https://i2.wp.com/www.starmometer.com/wp-content/uploads/2020/02/ABS-CBN-logo.jpg?fit=677%2C453&w=640",
    "address": "Punta Princesa Cebu City",
    "qr_code": [
      {
        "id": 1,
        "image": "/uploads/qr_code/image/1/thumb_5f7c1e34c13cd0ca1e88.png",
        "code": "1",
        "code_type": "check_in"
      },
      {
        "id": 2,
        "image": "/uploads/qr_code/image/1/thumb_5f7c1e34c13cd0ca1e88.png",
        "code": "2",
        "code_type": "check_in"
      },
      {
        "id": 3,
        "image": "/uploads/qr_code/image/1/thumb_5f7c1e34c13cd0ca1e88.png",
        "code": "3",
        "code_type": "check_in"
      }
    ]
  },
  "status": 200
}